drivit/__init__.py
drivit/document.py
drivit/drive.py
drivit/file.py
drivit/folder.py
drivit/service.py
drivit/spreadsheet.py
drivit-0.1.0.dist-info/METADATA
drivit-0.1.0.dist-info/WHEEL
drivit-0.1.0.dist-info/licenses/LICENSE
drivit-0.1.0.dist-info/RECORD
