Metadata-Version: 2.4
Name: drivit
Version: 0.1.0
Summary: A simple wrapper for the Google api python client
Project-URL: Homepage, https://github.com/mike-tr-adamson/drivit
Project-URL: Issues, https://github.com/mike-tr-adamson/drivit/issues
Author-email: Mike Adamson <mikeatdot@gmail.com>
License:                                  Apache License
License-File: LICENSE
Classifier: Development Status :: 3 - Alpha
Classifier: Intended Audience :: Developers
Classifier: License :: OSI Approved :: Apache Software License
Classifier: Operating System :: OS Independent
Classifier: Programming Language :: Python :: 3
Requires-Python: >=3.8
Requires-Dist: google-api-python-client>=2.131.0
Requires-Dist: ratelimiter>=1.2.0.post0
